setup.py
messenger_server_yury777.egg-info/PKG-INFO
messenger_server_yury777.egg-info/SOURCES.txt
messenger_server_yury777.egg-info/dependency_links.txt
messenger_server_yury777.egg-info/requires.txt
messenger_server_yury777.egg-info/top_level.txt
server/__init__.py
server/decors.py
server/descr.py
server/errors.py
server/meta.py
server/server.py
server/general/__init__.py
server/general/utils.py
server/general/variables.py
server/logs/__init__.py
server/logs/configs/__init__.py
server/logs/configs/config_client_log.py
server/logs/configs/config_server_log.py
server/project_unittests/__init__.py
server/project_unittests/test_client.py
server/project_unittests/test_server.py
server/project_unittests/test_utils.py
server/server/__init__.py
server/server/add_user.py
server/server/config_window.py
server/server/core.py
server/server/database.py
server/server/main_window.py
server/server/remove_user.py
server/server/stat_window.py