Metadata-Version: 1.0
Name: messenger-server-yury777
Version: 0.1
Summary: messenger_server
Home-page: UNKNOWN
Author: Yury Kim
Author-email: kimkrk84@mail.ru
License: UNKNOWN
Platform: UNKNOWN
